[{"Name": "Helmet", "Confidence": 99.98960876464844, "Instances": [{"BoundingBox": {"Width": 0.6870554685592651, "Height": 0.7268382906913757, "Left": 0.16394288837909698, "Top": 0.03988998010754585}, "Confidence": 99.98960876464844}], "Parents": [{"Name": "Clothing"}]}, {"Name": "Clothing", "Confidence": 99.98960876464844, "Instances": [], "Parents": []}, {"Name": "Apparel", "Confidence": 99.98960876464844, "Instances": [], "Parents": []}, {"Name": "Person", "Confidence": 97.98541259765625, "Instances": [{"BoundingBox": {"Width": 0.9234071969985962, "Height": 0.9176103472709656, "Left": 0.011204698123037815, "Top": 0.06305292993783951}, "Confidence": 97.98541259765625}], "Parents": []}, {"Name": "Human", "Confidence": 97.98541259765625, "Instances": [], "Parents": []}, {"Name": "Face", "Confidence": 95.77207946777344, "Instances": [], "Parents": [{"Name": "Person"}]}, {"Name": "Skin", "Confidence": 91.99154663085938, "Instances": [], "Parents": []}, {"Name": "Head", "Confidence": 87.93043518066406, "Instances": [], "Parents": []}, {"Name": "Call of Duty", "Confidence": 80.95530700683594, "Instances": [], "Parents": []}]