[{"Name": "Wheel", "Confidence": 99.66034698486328, "Instances": [{"BoundingBox": {"Width": 0.6304699778556824, "Height": 0.8043913245201111, "Left": 0.27466070652008057, "Top": 0.17234735190868378}, "Confidence": 99.66034698486328}], "Parents": [{"Name": "Machine"}]}, {"Name": "Machine", "Confidence": 99.66034698486328, "Instances": [], "Parents": []}, {"Name": "Bicycle", "Confidence": 98.73995208740234, "Instances": [{"BoundingBox": {"Width": 0.8044407963752747, "Height": 0.9865759611129761, "Left": 0.19486473500728607, "Top": 0.0}, "Confidence": 98.73995208740234}], "Parents": [{"Name": "Vehicle"}, {"Name": "Transportation"}]}, {"Name": "Bike", "Confidence": 98.73995208740234, "Instances": [], "Parents": [{"Name": "Vehicle"}, {"Name": "Transportation"}]}, {"Name": "Vehicle", "Confidence": 98.73995208740234, "Instances": [], "Parents": [{"Name": "Transportation"}]}, {"Name": "Transportation", "Confidence": 98.73995208740234, "Instances": [], "Parents": []}, {"Name": "Mountain Bike", "Confidence": 93.6715087890625, "Instances": [], "Parents": [{"Name": "Bicycle"}, {"Name": "Vehicle"}, {"Name": "Transportation"}]}, {"Name": "Spoke", "Confidence": 84.89116668701172, "Instances": [], "Parents": [{"Name": "Machine"}]}]