[{"Name": "Wheel", "Confidence": 99.642822265625, "Instances": [{"BoundingBox": {"Width": 0.4346802830696106, "Height": 0.48436182737350464, "Left": 0.5637572407722473, "Top": 0.43383151292800903}, "Confidence": 99.642822265625}, {"BoundingBox": {"Width": 0.23885145783424377, "Height": 0.38156041502952576, "Left": 0.10313411056995392, "Top": 0.5563193559646606}, "Confidence": 99.50799560546875}], "Parents": [{"Name": "Machine"}]}, {"Name": "Machine", "Confidence": 99.642822265625, "Instances": [], "Parents": []}, {"Name": "Bicycle", "Confidence": 99.43700408935547, "Instances": [{"BoundingBox": {"Width": 0.8569591641426086, "Height": 0.7508277893066406, "Left": 0.10911822319030762, "Top": 0.20067575573921204}, "Confidence": 99.43700408935547}], "Parents": [{"Name": "Vehicle"}, {"Name": "Transportation"}]}, {"Name": "Bike", "Confidence": 99.43700408935547, "Instances": [], "Parents": [{"Name": "Vehicle"}, {"Name": "Transportation"}]}, {"Name": "Vehicle", "Confidence": 99.43700408935547, "Instances": [], "Parents": [{"Name": "Transportation"}]}, {"Name": "Transportation", "Confidence": 99.43700408935547, "Instances": [], "Parents": []}, {"Name": "Mountain Bike", "Confidence": 98.48739624023438, "Instances": [], "Parents": [{"Name": "Bicycle"}, {"Name": "Vehicle"}, {"Name": "Transportation"}]}, {"Name": "Tree", "Confidence": 83.44331359863281, "Instances": [], "Parents": [{"Name": "Plant"}]}, {"Name": "Plant", "Confidence": 83.44331359863281, "Instances": [], "Parents": []}]