[{"Name": "Bicycle", "Confidence": 99.92225646972656, "Instances": [{"BoundingBox": {"Width": 0.8135427832603455, "Height": 0.3478595018386841, "Left": 0.07661142945289612, "Top": 0.6508617401123047}, "Confidence": 99.92225646972656}], "Parents": [{"Name": "Vehicle"}, {"Name": "Transportation"}]}, {"Name": "Bike", "Confidence": 99.92225646972656, "Instances": [], "Parents": [{"Name": "Vehicle"}, {"Name": "Transportation"}]}, {"Name": "Vehicle", "Confidence": 99.92225646972656, "Instances": [], "Parents": [{"Name": "Transportation"}]}, {"Name": "Transportation", "Confidence": 99.92225646972656, "Instances": [], "Parents": []}, {"Name": "Wheel", "Confidence": 99.54576873779297, "Instances": [{"BoundingBox": {"Width": 0.2922574281692505, "Height": 0.20286352932453156, "Left": 0.5920142531394958, "Top": 0.7883462905883789}, "Confidence": 99.54576873779297}, {"BoundingBox": {"Width": 0.28056764602661133, "Height": 0.19900567829608917, "Left": 0.07873784750699997, "Top": 0.7942113280296326}, "Confidence": 99.33415985107422}], "Parents": [{"Name": "Machine"}]}, {"Name": "Machine", "Confidence": 99.54576873779297, "Instances": [], "Parents": []}, {"Name": "Mountain Bike", "Confidence": 97.47476959228516, "Instances": [], "Parents": [{"Name": "Bicycle"}, {"Name": "Vehicle"}, {"Name": "Transportation"}]}]