[{"Name": "Wheel", "Confidence": 99.90444946289062, "Instances": [{"BoundingBox": {"Width": 0.49107393622398376, "Height": 0.6116197109222412, "Left": 0.0030086657498031855, "Top": 0.324365496635437}, "Confidence": 99.90444946289062}, {"BoundingBox": {"Width": 0.26745662093162537, "Height": 0.4235726594924927, "Left": 0.711067259311676, "Top": 0.32094332575798035}, "Confidence": 98.17073059082031}, {"BoundingBox": {"Width": 0.22194507718086243, "Height": 0.323574036359787, "Left": 0.5505385994911194, "Top": 0.3600514233112335}, "Confidence": 95.23292541503906}], "Parents": [{"Name": "Machine"}]}, {"Name": "Machine", "Confidence": 99.90444946289062, "Instances": [], "Parents": []}, {"Name": "Bicycle", "Confidence": 99.87108612060547, "Instances": [{"BoundingBox": {"Width": 0.9162171483039856, "Height": 0.896598219871521, "Left": 0.04424325376749039, "Top": 0.037034887820482254}, "Confidence": 99.87108612060547}], "Parents": [{"Name": "Vehicle"}, {"Name": "Transportation"}]}, {"Name": "Bike", "Confidence": 99.87108612060547, "Instances": [], "Parents": [{"Name": "Vehicle"}, {"Name": "Transportation"}]}, {"Name": "Vehicle", "Confidence": 99.87108612060547, "Instances": [], "Parents": [{"Name": "Transportation"}]}, {"Name": "Transportation", "Confidence": 99.87108612060547, "Instances": [], "Parents": []}, {"Name": "Mountain Bike", "Confidence": 88.5621337890625, "Instances": [], "Parents": [{"Name": "Bicycle"}, {"Name": "Vehicle"}, {"Name": "Transportation"}]}]