[{"Name": "Bicycle", "Confidence": 99.90457916259766, "Instances": [{"BoundingBox": {"Width": 0.5170440673828125, "Height": 0.33879101276397705, "Left": 0.2742491662502289, "Top": 0.5532666444778442}, "Confidence": 99.90457916259766}], "Parents": [{"Name": "Vehicle"}, {"Name": "Transportation"}]}, {"Name": "Bike", "Confidence": 99.90457916259766, "Instances": [], "Parents": [{"Name": "Vehicle"}, {"Name": "Transportation"}]}, {"Name": "Vehicle", "Confidence": 99.90457916259766, "Instances": [], "Parents": [{"Name": "Transportation"}]}, {"Name": "Transportation", "Confidence": 99.90457916259766, "Instances": [], "Parents": []}, {"Name": "Wheel", "Confidence": 99.6572036743164, "Instances": [{"BoundingBox": {"Width": 0.21447177231311798, "Height": 0.2172320932149887, "Left": 0.27943071722984314, "Top": 0.6786882877349854}, "Confidence": 99.6572036743164}, {"BoundingBox": {"Width": 0.18266484141349792, "Height": 0.20067940652370453, "Left": 0.6011428833007812, "Top": 0.6717435121536255}, "Confidence": 98.536376953125}], "Parents": [{"Name": "Machine"}]}, {"Name": "Machine", "Confidence": 99.6572036743164, "Instances": [], "Parents": []}, {"Name": "Mountain Bike", "Confidence": 97.87934875488281, "Instances": [], "Parents": [{"Name": "Bicycle"}, {"Name": "Vehicle"}, {"Name": "Transportation"}]}]