[{"Name": "Clothing", "Confidence": 99.99710083007812, "Instances": [], "Parents": []}, {"Name": "Apparel", "Confidence": 99.99710083007812, "Instances": [], "Parents": []}, {"Name": "Helmet", "Confidence": 99.9631576538086, "Instances": [{"BoundingBox": {"Width": 0.17791756987571716, "Height": 0.29133784770965576, "Left": 0.3437407612800598, "Top": 0.2800438702106476}, "Confidence": 99.85540771484375}], "Parents": [{"Name": "Clothing"}]}, {"Name": "Crash Helmet", "Confidence": 99.9493179321289, "Instances": [], "Parents": [{"Name": "Helmet"}, {"Name": "Clothing"}]}, {"Name": "Person", "Confidence": 99.54275512695312, "Instances": [{"BoundingBox": {"Width": 0.08760376274585724, "Height": 0.26761072874069214, "Left": 0.9028857946395874, "Top": 0.23924127221107483}, "Confidence": 99.54275512695312}, {"BoundingBox": {"Width": 0.529902458190918, "Height": 0.5179935693740845, "Left": 0.09445847570896149, "Top": 0.2771399915218353}, "Confidence": 99.46141052246094}], "Parents": []}, {"Name": "Wheel", "Confidence": 96.991455078125, "Instances": [{"BoundingBox": {"Width": 0.06297387182712555, "Height": 0.09574546664953232, "Left": 0.8447109460830688, "Top": 0.41291770339012146}, "Confidence": 96.991455078125}, {"BoundingBox": {"Width": 0.08793928474187851, "Height": 0.09188022464513779, "Left": 0.6283354759216309, "Top": 0.48087579011917114}, "Confidence": 77.60277557373047}], "Parents": [{"Name": "Machine"}]}, {"Name": "Machine", "Confidence": 96.991455078125, "Instances": [], "Parents": []}, {"Name": "Bicycle", "Confidence": 90.3600082397461, "Instances": [{"BoundingBox": {"Width": 0.2508701682090759, "Height": 0.204036146402359, "Left": 0.5173377394676208, "Top": 0.40400180220603943}, "Confidence": 90.3600082397461}, {"BoundingBox": {"Width": 0.11945461481809616, "Height": 0.1714179962873459, "Left": 0.8406535387039185, "Top": 0.339912474155426}, "Confidence": 88.15985107421875}], "Parents": [{"Name": "Vehicle"}, {"Name": "Transportation"}]}, {"Name": "Transportation", "Confidence": 90.3600082397461, "Instances": [], "Parents": []}, {"Name": "Vehicle", "Confidence": 90.3600082397461, "Instances": [], "Parents": [{"Name": "Transportation"}]}]