[{"Name": "Bicycle", "Confidence": 98.20796966552734, "Instances": [{"BoundingBox": {"Width": 0.9941773414611816, "Height": 0.8642932772636414, "Left": 0.0051282248459756374, "Top": 0.13166697323322296}, "Confidence": 98.20796966552734}], "Parents": [{"Name": "Vehicle"}, {"Name": "Transportation"}]}, {"Name": "Transportation", "Confidence": 98.20796966552734, "Instances": [], "Parents": []}, {"Name": "Vehicle", "Confidence": 98.20796966552734, "Instances": [], "Parents": [{"Name": "Transportation"}]}, {"Name": "Bike", "Confidence": 98.20796966552734, "Instances": [], "Parents": [{"Name": "Vehicle"}, {"Name": "Transportation"}]}, {"Name": "Spoke", "Confidence": 96.58285522460938, "Instances": [], "Parents": [{"Name": "Machine"}]}, {"Name": "Machine", "Confidence": 96.58285522460938, "Instances": [], "Parents": []}, {"Name": "Wheel", "Confidence": 96.1108169555664, "Instances": [{"BoundingBox": {"Width": 0.9267561435699463, "Height": 0.7421521544456482, "Left": 0.03333210572600365, "Top": 0.2510758936405182}, "Confidence": 94.4006118774414}], "Parents": [{"Name": "Machine"}]}, {"Name": "Tire", "Confidence": 94.21602630615234, "Instances": [], "Parents": []}]