[{"Name": "Bicycle", "Confidence": 99.57585906982422, "Instances": [{"BoundingBox": {"Width": 0.27168557047843933, "Height": 0.21894370019435883, "Left": 0.5374854803085327, "Top": 0.41717538237571716}, "Confidence": 99.57585906982422}, {"BoundingBox": {"Width": 0.19078539311885834, "Height": 0.270487904548645, "Left": 0.6249841451644897, "Top": 0.4455982744693756}, "Confidence": 90.01301574707031}], "Parents": [{"Name": "Vehicle"}, {"Name": "Transportation"}]}, {"Name": "Bike", "Confidence": 99.57585906982422, "Instances": [], "Parents": [{"Name": "Vehicle"}, {"Name": "Transportation"}]}, {"Name": "Vehicle", "Confidence": 99.57585906982422, "Instances": [], "Parents": [{"Name": "Transportation"}]}, {"Name": "Transportation", "Confidence": 99.57585906982422, "Instances": [], "Parents": []}, {"Name": "Person", "Confidence": 98.17481994628906, "Instances": [{"BoundingBox": {"Width": 0.14936897158622742, "Height": 0.2628194987773895, "Left": 0.6628504395484924, "Top": 0.31274718046188354}, "Confidence": 98.17481994628906}], "Parents": []}, {"Name": "Mountain Bike", "Confidence": 97.95677185058594, "Instances": [], "Parents": [{"Name": "Bicycle"}, {"Name": "Vehicle"}, {"Name": "Transportation"}]}, {"Name": "Wheel", "Confidence": 95.98779296875, "Instances": [{"BoundingBox": {"Width": 0.1267322599887848, "Height": 0.1500307321548462, "Left": 0.662804365158081, "Top": 0.5774304270744324}, "Confidence": 95.98779296875}, {"BoundingBox": {"Width": 0.18688884377479553, "Height": 0.11699642241001129, "Left": 0.539576530456543, "Top": 0.4858236014842987}, "Confidence": 95.72966003417969}], "Parents": [{"Name": "Machine"}]}, {"Name": "Machine", "Confidence": 95.98779296875, "Instances": [], "Parents": []}, {"Name": "Tree", "Confidence": 83.8288345336914, "Instances": [], "Parents": [{"Name": "Plant"}]}, {"Name": "Plant", "Confidence": 83.8288345336914, "Instances": [], "Parents": []}]