[{"Name": "Bicycle", "Confidence": 99.98375701904297, "Instances": [{"BoundingBox": {"Width": 0.8480288982391357, "Height": 0.8164074420928955, "Left": 0.07096429169178009, "Top": 0.09008769690990448}, "Confidence": 99.98375701904297}], "Parents": [{"Name": "Vehicle"}, {"Name": "Transportation"}]}, {"Name": "Bike", "Confidence": 99.98375701904297, "Instances": [], "Parents": [{"Name": "Vehicle"}, {"Name": "Transportation"}]}, {"Name": "Vehicle", "Confidence": 99.98375701904297, "Instances": [], "Parents": [{"Name": "Transportation"}]}, {"Name": "Transportation", "Confidence": 99.98375701904297, "Instances": [], "Parents": []}, {"Name": "Wheel", "Confidence": 99.97752380371094, "Instances": [{"BoundingBox": {"Width": 0.33756667375564575, "Height": 0.4768989682197571, "Left": 0.5871774554252625, "Top": 0.40413200855255127}, "Confidence": 99.97752380371094}, {"BoundingBox": {"Width": 0.3169509172439575, "Height": 0.48133423924446106, "Left": 0.05109553411602974, "Top": 0.4156728684902191}, "Confidence": 99.97317504882812}], "Parents": [{"Name": "Machine"}]}, {"Name": "Machine", "Confidence": 99.97752380371094, "Instances": [], "Parents": []}, {"Name": "Mountain Bike", "Confidence": 98.18080139160156, "Instances": [], "Parents": [{"Name": "Bicycle"}, {"Name": "Vehicle"}, {"Name": "Transportation"}]}]