[{"Name": "Bicycle", "Confidence": 93.22538757324219, "Instances": [{"BoundingBox": {"Width": 0.9862743020057678, "Height": 0.9234905242919922, "Left": 0.0, "Top": 0.07072600722312927}, "Confidence": 87.25148010253906}], "Parents": [{"Name": "Vehicle"}, {"Name": "Transportation"}]}, {"Name": "Bike", "Confidence": 93.22538757324219, "Instances": [], "Parents": [{"Name": "Vehicle"}, {"Name": "Transportation"}]}, {"Name": "Vehicle", "Confidence": 93.22538757324219, "Instances": [], "Parents": [{"Name": "Transportation"}]}, {"Name": "Transportation", "Confidence": 93.22538757324219, "Instances": [], "Parents": []}, {"Name": "Machine", "Confidence": 80.04202270507812, "Instances": [], "Parents": []}]