[{"Name": "Person", "Confidence": 99.8593521118164, "Instances": [{"BoundingBox": {"Width": 0.3788783848285675, "Height": 0.8274602890014648, "Left": 0.6133776307106018, "Top": 0.15773361921310425}, "Confidence": 99.8593521118164}], "Parents": []}, {"Name": "Human", "Confidence": 99.8593521118164, "Instances": [], "Parents": []}, {"Name": "Bicycle", "Confidence": 99.80143737792969, "Instances": [{"BoundingBox": {"Width": 0.8640652298927307, "Height": 0.5027817487716675, "Left": 0.002369124908000231, "Top": 0.4964769780635834}, "Confidence": 99.80143737792969}], "Parents": [{"Name": "Vehicle"}, {"Name": "Transportation"}]}, {"Name": "Vehicle", "Confidence": 99.80143737792969, "Instances": [], "Parents": [{"Name": "Transportation"}]}, {"Name": "Transportation", "Confidence": 99.80143737792969, "Instances": [], "Parents": []}, {"Name": "Wheel", "Confidence": 94.91485595703125, "Instances": [{"BoundingBox": {"Width": 0.22584502398967743, "Height": 0.08528253436088562, "Left": 0.0004574175109155476, "Top": 0.9139761924743652}, "Confidence": 94.91485595703125}], "Parents": [{"Name": "Machine"}]}, {"Name": "Machine", "Confidence": 94.91485595703125, "Instances": [], "Parents": []}, {"Name": "Glasses", "Confidence": 89.84280395507812, "Instances": [{"BoundingBox": {"Width": 0.19903519749641418, "Height": 0.09071851521730423, "Left": 0.7046278119087219, "Top": 0.23183733224868774}, "Confidence": 89.84280395507812}], "Parents": [{"Name": "Accessories"}]}, {"Name": "Accessories", "Confidence": 89.84280395507812, "Instances": [], "Parents": []}, {"Name": "Spoke", "Confidence": 84.1692886352539, "Instances": [], "Parents": [{"Name": "Machine"}]}]