[{"Name": "Bicycle", "Confidence": 99.7294921875, "Instances": [{"BoundingBox": {"Width": 0.845339298248291, "Height": 0.9860693216323853, "Left": 0.018354246392846107, "Top": 0.013249410316348076}, "Confidence": 99.7294921875}], "Parents": [{"Name": "Vehicle"}, {"Name": "Transportation"}]}, {"Name": "Transportation", "Confidence": 99.7294921875, "Instances": [], "Parents": []}, {"Name": "Vehicle", "Confidence": 99.7294921875, "Instances": [], "Parents": [{"Name": "Transportation"}]}, {"Name": "Bike", "Confidence": 99.7294921875, "Instances": [], "Parents": [{"Name": "Vehicle"}, {"Name": "Transportation"}]}]