[{"Name": "Person", "Confidence": 97.20980834960938, "Instances": [{"BoundingBox": {"Width": 0.13619978725910187, "Height": 0.13964365422725677, "Left": 0.37463128566741943, "Top": 0.20649448037147522}, "Confidence": 97.20980834960938}], "Parents": []}, {"Name": "Human", "Confidence": 97.20980834960938, "Instances": [], "Parents": []}, {"Name": "Slope", "Confidence": 97.0919189453125, "Instances": [], "Parents": []}, {"Name": "Vehicle", "Confidence": 94.50428009033203, "Instances": [], "Parents": [{"Name": "Transportation"}]}, {"Name": "Transportation", "Confidence": 94.50428009033203, "Instances": [], "Parents": []}, {"Name": "Motorcycle", "Confidence": 90.85936737060547, "Instances": [{"BoundingBox": {"Width": 0.22898848354816437, "Height": 0.16098998486995697, "Left": 0.35571759939193726, "Top": 0.23317308723926544}, "Confidence": 90.85936737060547}], "Parents": [{"Name": "Vehicle"}, {"Name": "Transportation"}]}, {"Name": "Bicycle", "Confidence": 89.62957763671875, "Instances": [{"BoundingBox": {"Width": 0.23865839838981628, "Height": 0.14789719879627228, "Left": 0.3439283072948456, "Top": 0.24833597242832184}, "Confidence": 83.48617553710938}], "Parents": [{"Name": "Vehicle"}, {"Name": "Transportation"}]}, {"Name": "Soil", "Confidence": 83.20506286621094, "Instances": [], "Parents": []}, {"Name": "Adventure", "Confidence": 80.80848693847656, "Instances": [], "Parents": [{"Name": "Leisure Activities"}]}, {"Name": "Leisure Activities", "Confidence": 80.80848693847656, "Instances": [], "Parents": []}]