[{"Name": "Person", "Confidence": 99.66234588623047, "Instances": [{"BoundingBox": {"Width": 0.1042700856924057, "Height": 0.23916959762573242, "Left": 0.7186620831489563, "Top": 0.5323588252067566}, "Confidence": 99.66234588623047}, {"BoundingBox": {"Width": 0.08686760812997818, "Height": 0.24885359406471252, "Left": 0.6306355595588684, "Top": 0.5484752655029297}, "Confidence": 99.34326171875}, {"BoundingBox": {"Width": 0.0796324834227562, "Height": 0.20718243718147278, "Left": 0.530274510383606, "Top": 0.5004598498344421}, "Confidence": 98.74092102050781}, {"BoundingBox": {"Width": 0.10472726076841354, "Height": 0.2261463850736618, "Left": 0.4471750557422638, "Top": 0.5018215179443359}, "Confidence": 97.11741638183594}, {"BoundingBox": {"Width": 0.15514640510082245, "Height": 0.26580923795700073, "Left": 0.23093193769454956, "Top": 0.4521082639694214}, "Confidence": 71.31078338623047}, {"BoundingBox": {"Width": 0.11799892783164978, "Height": 0.17519091069698334, "Left": 0.22395309805870056, "Top": 0.5190639495849609}, "Confidence": 59.10490417480469}], "Parents": []}, {"Name": "Human", "Confidence": 99.66234588623047, "Instances": [], "Parents": []}, {"Name": "Bicycle", "Confidence": 90.55121612548828, "Instances": [{"BoundingBox": {"Width": 0.23147758841514587, "Height": 0.20225581526756287, "Left": 0.2160029262304306, "Top": 0.5777782201766968}, "Confidence": 90.55121612548828}], "Parents": [{"Name": "Vehicle"}, {"Name": "Transportation"}]}, {"Name": "Bike", "Confidence": 90.55121612548828, "Instances": [], "Parents": [{"Name": "Vehicle"}, {"Name": "Transportation"}]}, {"Name": "Transportation", "Confidence": 90.55121612548828, "Instances": [], "Parents": []}, {"Name": "Vehicle", "Confidence": 90.55121612548828, "Instances": [], "Parents": [{"Name": "Transportation"}]}, {"Name": "Vegetation", "Confidence": 87.5560302734375, "Instances": [], "Parents": [{"Name": "Plant"}]}, {"Name": "Plant", "Confidence": 87.5560302734375, "Instances": [], "Parents": []}, {"Name": "Outdoors", "Confidence": 83.8621826171875, "Instances": [], "Parents": []}, {"Name": "Tree", "Confidence": 81.51458740234375, "Instances": [], "Parents": [{"Name": "Plant"}]}]