[{"Name": "Bicycle", "Confidence": 91.42054748535156, "Instances": [{"BoundingBox": {"Width": 0.9684365391731262, "Height": 0.9973737001419067, "Left": 0.009083345532417297, "Top": 0.0}, "Confidence": 91.42054748535156}], "Parents": [{"Name": "Vehicle"}, {"Name": "Transportation"}]}, {"Name": "Bike", "Confidence": 91.42054748535156, "Instances": [], "Parents": [{"Name": "Vehicle"}, {"Name": "Transportation"}]}, {"Name": "Transportation", "Confidence": 91.42054748535156, "Instances": [], "Parents": []}, {"Name": "Vehicle", "Confidence": 91.42054748535156, "Instances": [], "Parents": [{"Name": "Transportation"}]}, {"Name": "Gun", "Confidence": 84.21141815185547, "Instances": [{"BoundingBox": {"Width": 0.8626805543899536, "Height": 0.9284778833389282, "Left": 0.008752483874559402, "Top": 0.03345291316509247}, "Confidence": 84.21141815185547}], "Parents": [{"Name": "Weapon"}]}, {"Name": "Weapon", "Confidence": 84.21141815185547, "Instances": [], "Parents": []}, {"Name": "Weaponry", "Confidence": 84.21141815185547, "Instances": [], "Parents": []}]