[{"Name": "Wheel", "Confidence": 99.98725128173828, "Instances": [{"BoundingBox": {"Width": 0.2779000997543335, "Height": 0.4329237639904022, "Left": 0.5546182990074158, "Top": 0.47762158513069153}, "Confidence": 99.98725128173828}, {"BoundingBox": {"Width": 0.28505104780197144, "Height": 0.43968620896339417, "Left": 0.1147308349609375, "Top": 0.472442626953125}, "Confidence": 99.90680694580078}], "Parents": [{"Name": "Machine"}]}, {"Name": "Machine", "Confidence": 99.98725128173828, "Instances": [], "Parents": []}, {"Name": "Bicycle", "Confidence": 99.98477172851562, "Instances": [{"BoundingBox": {"Width": 0.7349086999893188, "Height": 0.711883544921875, "Left": 0.11556756496429443, "Top": 0.2235943228006363}, "Confidence": 99.98477172851562}], "Parents": [{"Name": "Vehicle"}, {"Name": "Transportation"}]}, {"Name": "Bike", "Confidence": 99.98477172851562, "Instances": [], "Parents": [{"Name": "Vehicle"}, {"Name": "Transportation"}]}, {"Name": "Vehicle", "Confidence": 99.98477172851562, "Instances": [], "Parents": [{"Name": "Transportation"}]}, {"Name": "Transportation", "Confidence": 99.98477172851562, "Instances": [], "Parents": []}, {"Name": "Mountain Bike", "Confidence": 81.12306213378906, "Instances": [], "Parents": [{"Name": "Bicycle"}, {"Name": "Vehicle"}, {"Name": "Transportation"}]}]