[{"Name": "Bicycle", "Confidence": 94.10675811767578, "Instances": [{"BoundingBox": {"Width": 0.6665016412734985, "Height": 0.5328026413917542, "Left": 0.019341956824064255, "Top": 0.11899717152118683}, "Confidence": 74.23637390136719}], "Parents": [{"Name": "Vehicle"}, {"Name": "Transportation"}]}, {"Name": "Bike", "Confidence": 94.10675811767578, "Instances": [], "Parents": [{"Name": "Vehicle"}, {"Name": "Transportation"}]}, {"Name": "Vehicle", "Confidence": 94.10675811767578, "Instances": [], "Parents": [{"Name": "Transportation"}]}, {"Name": "Transportation", "Confidence": 94.10675811767578, "Instances": [], "Parents": []}]