[{"Name": "Bicycle", "Confidence": 98.390380859375, "Instances": [{"BoundingBox": {"Width": 0.11316545307636261, "Height": 0.2012198567390442, "Left": 0.3997562825679779, "Top": 0.46334388852119446}, "Confidence": 98.390380859375}], "Parents": [{"Name": "Vehicle"}, {"Name": "Transportation"}]}, {"Name": "Bike", "Confidence": 98.390380859375, "Instances": [], "Parents": [{"Name": "Vehicle"}, {"Name": "Transportation"}]}, {"Name": "Vehicle", "Confidence": 98.390380859375, "Instances": [], "Parents": [{"Name": "Transportation"}]}, {"Name": "Transportation", "Confidence": 98.390380859375, "Instances": [], "Parents": []}, {"Name": "Person", "Confidence": 97.45362091064453, "Instances": [{"BoundingBox": {"Width": 0.1307864785194397, "Height": 0.24205432832241058, "Left": 0.3832028806209564, "Top": 0.3721622824668884}, "Confidence": 97.45362091064453}], "Parents": []}, {"Name": "Human", "Confidence": 97.45362091064453, "Instances": [], "Parents": []}, {"Name": "Mountain Bike", "Confidence": 94.76394653320312, "Instances": [], "Parents": [{"Name": "Bicycle"}, {"Name": "Vehicle"}, {"Name": "Transportation"}]}, {"Name": "Helmet", "Confidence": 89.0503158569336, "Instances": [{"BoundingBox": {"Width": 0.048153940588235855, "Height": 0.053187813609838486, "Left": 0.40108659863471985, "Top": 0.3743444085121155}, "Confidence": 89.0503158569336}], "Parents": [{"Name": "Clothing"}]}, {"Name": "Clothing", "Confidence": 89.0503158569336, "Instances": [], "Parents": []}, {"Name": "Slope", "Confidence": 86.01054382324219, "Instances": [], "Parents": []}]