[{"Name": "Collage", "Confidence": 99.64319610595703, "Instances": [], "Parents": [{"Name": "Poster"}, {"Name": "Advertisement"}]}, {"Name": "Advertisement", "Confidence": 99.64319610595703, "Instances": [], "Parents": []}, {"Name": "Poster", "Confidence": 99.64319610595703, "Instances": [], "Parents": [{"Name": "Advertisement"}]}, {"Name": "Person", "Confidence": 99.57630157470703, "Instances": [{"BoundingBox": {"Width": 0.42920464277267456, "Height": 0.37590327858924866, "Left": 0.1683536320924759, "Top": 0.11332576721906662}, "Confidence": 99.57630157470703}, {"BoundingBox": {"Width": 0.30690085887908936, "Height": 0.3713616132736206, "Left": 0.5792844891548157, "Top": 0.1324867308139801}, "Confidence": 99.31769561767578}, {"BoundingBox": {"Width": 0.0687953531742096, "Height": 0.11237570643424988, "Left": 0.594417929649353, "Top": 0.10770402103662491}, "Confidence": 98.44597625732422}, {"BoundingBox": {"Width": 0.23053434491157532, "Height": 0.16496619582176208, "Left": 0.34884610772132874, "Top": 0.740637481212616}, "Confidence": 98.24691772460938}], "Parents": []}, {"Name": "Human", "Confidence": 99.57630157470703, "Instances": [], "Parents": []}, {"Name": "Clothing", "Confidence": 88.01703643798828, "Instances": [], "Parents": []}, {"Name": "Apparel", "Confidence": 88.01703643798828, "Instances": [], "Parents": []}, {"Name": "Plant", "Confidence": 87.87493896484375, "Instances": [], "Parents": []}, {"Name": "Chair", "Confidence": 87.39389038085938, "Instances": [], "Parents": [{"Name": "Furniture"}]}, {"Name": "Furniture", "Confidence": 87.39389038085938, "Instances": [], "Parents": []}]