[{"Name": "Wheel", "Confidence": 99.98565673828125, "Instances": [{"BoundingBox": {"Width": 0.3636826276779175, "Height": 0.5971545577049255, "Left": 0.6184687614440918, "Top": 0.33184415102005005}, "Confidence": 99.98565673828125}, {"BoundingBox": {"Width": 0.3774493336677551, "Height": 0.6020410060882568, "Left": 0.006986374035477638, "Top": 0.34012725949287415}, "Confidence": 99.9709243774414}], "Parents": [{"Name": "Machine"}]}, {"Name": "Machine", "Confidence": 99.98565673828125, "Instances": [], "Parents": []}, {"Name": "Bicycle", "Confidence": 99.95783233642578, "Instances": [{"BoundingBox": {"Width": 0.922676146030426, "Height": 0.9078865051269531, "Left": 0.027919769287109375, "Top": 0.047412510961294174}, "Confidence": 99.95783233642578}], "Parents": [{"Name": "Vehicle"}, {"Name": "Transportation"}]}, {"Name": "Bike", "Confidence": 99.95783233642578, "Instances": [], "Parents": [{"Name": "Vehicle"}, {"Name": "Transportation"}]}, {"Name": "Vehicle", "Confidence": 99.95783233642578, "Instances": [], "Parents": [{"Name": "Transportation"}]}, {"Name": "Transportation", "Confidence": 99.95783233642578, "Instances": [], "Parents": []}, {"Name": "Mountain Bike", "Confidence": 83.64852142333984, "Instances": [], "Parents": [{"Name": "Bicycle"}, {"Name": "Vehicle"}, {"Name": "Transportation"}]}]