[{"Name": "Bicycle", "Confidence": 99.22917938232422, "Instances": [{"BoundingBox": {"Width": 0.1518557220697403, "Height": 0.38580456376075745, "Left": 0.38226237893104553, "Top": 0.33988043665885925}, "Confidence": 99.22917938232422}], "Parents": [{"Name": "Vehicle"}, {"Name": "Transportation"}]}, {"Name": "Vehicle", "Confidence": 99.22917938232422, "Instances": [], "Parents": [{"Name": "Transportation"}]}, {"Name": "Transportation", "Confidence": 99.22917938232422, "Instances": [], "Parents": []}, {"Name": "Person", "Confidence": 98.92280578613281, "Instances": [{"BoundingBox": {"Width": 0.0908036157488823, "Height": 0.4000972509384155, "Left": 0.4390338957309723, "Top": 0.19856619834899902}, "Confidence": 98.92280578613281}], "Parents": []}, {"Name": "Vegetation", "Confidence": 97.88190460205078, "Instances": [], "Parents": []}, {"Name": "Slope", "Confidence": 97.26687622070312, "Instances": [], "Parents": []}, {"Name": "Path", "Confidence": 94.74341583251953, "Instances": [], "Parents": []}, {"Name": "Wheel", "Confidence": 90.66826629638672, "Instances": [{"BoundingBox": {"Width": 0.07056545466184616, "Height": 0.21750321984291077, "Left": 0.3815195858478546, "Top": 0.3670622408390045}, "Confidence": 90.66826629638672}], "Parents": []}, {"Name": "Helmet", "Confidence": 90.0238265991211, "Instances": [{"BoundingBox": {"Width": 0.04755299910902977, "Height": 0.09605817496776581, "Left": 0.45268914103507996, "Top": 0.1960962563753128}, "Confidence": 90.0238265991211}], "Parents": []}, {"Name": "Mountain Bike", "Confidence": 86.22984313964844, "Instances": [], "Parents": [{"Name": "Bicycle"}, {"Name": "Vehicle"}, {"Name": "Transportation"}]}]