[{"Name": "Bicycle", "Confidence": 98.74738311767578, "Instances": [{"BoundingBox": {"Width": 0.19241973757743835, "Height": 0.16870906949043274, "Left": 0.2823359966278076, "Top": 0.52256840467453}, "Confidence": 98.74738311767578}], "Parents": [{"Name": "Vehicle"}, {"Name": "Transportation"}]}, {"Name": "Bike", "Confidence": 98.74738311767578, "Instances": [], "Parents": [{"Name": "Vehicle"}, {"Name": "Transportation"}]}, {"Name": "Transportation", "Confidence": 98.74738311767578, "Instances": [], "Parents": []}, {"Name": "Vehicle", "Confidence": 98.74738311767578, "Instances": [], "Parents": [{"Name": "Transportation"}]}, {"Name": "Person", "Confidence": 97.83374786376953, "Instances": [{"BoundingBox": {"Width": 0.0993051752448082, "Height": 0.2200494259595871, "Left": 0.35756421089172363, "Top": 0.4470750093460083}, "Confidence": 97.83374786376953}], "Parents": []}, {"Name": "Human", "Confidence": 97.83374786376953, "Instances": [], "Parents": []}, {"Name": "Mountain Bike", "Confidence": 95.66727447509766, "Instances": [], "Parents": [{"Name": "Bicycle"}, {"Name": "Vehicle"}, {"Name": "Transportation"}]}, {"Name": "Wheel", "Confidence": 93.16162109375, "Instances": [{"BoundingBox": {"Width": 0.08795108646154404, "Height": 0.09230069071054459, "Left": 0.28281649947166443, "Top": 0.5700017213821411}, "Confidence": 93.16162109375}, {"BoundingBox": {"Width": 0.0622054748237133, "Height": 0.06708021461963654, "Left": 0.40894898772239685, "Top": 0.5877947807312012}, "Confidence": 80.23770141601562}], "Parents": [{"Name": "Machine"}]}, {"Name": "Machine", "Confidence": 93.16162109375, "Instances": [], "Parents": []}]