[{"Name": "Bicycle", "Confidence": 99.90180969238281, "Instances": [{"BoundingBox": {"Width": 0.4425845444202423, "Height": 0.3487437069416046, "Left": 0.5262917876243591, "Top": 0.649380087852478}, "Confidence": 99.90180969238281}, {"BoundingBox": {"Width": 0.25275298953056335, "Height": 0.3588045537471771, "Left": 0.7344119548797607, "Top": 0.6369668245315552}, "Confidence": 83.33623504638672}], "Parents": [{"Name": "Vehicle"}, {"Name": "Transportation"}]}, {"Name": "Bike", "Confidence": 99.90180969238281, "Instances": [], "Parents": [{"Name": "Vehicle"}, {"Name": "Transportation"}]}, {"Name": "Transportation", "Confidence": 99.90180969238281, "Instances": [], "Parents": []}, {"Name": "Vehicle", "Confidence": 99.90180969238281, "Instances": [], "Parents": [{"Name": "Transportation"}]}, {"Name": "Person", "Confidence": 99.86328887939453, "Instances": [{"BoundingBox": {"Width": 0.22718963027000427, "Height": 0.6674625873565674, "Left": 0.627412736415863, "Top": 0.33066123723983765}, "Confidence": 99.86328887939453}, {"BoundingBox": {"Width": 0.14135055243968964, "Height": 0.5601596832275391, "Left": 0.816100001335144, "Top": 0.356709748506546}, "Confidence": 99.84896850585938}], "Parents": []}, {"Name": "Human", "Confidence": 99.86328887939453, "Instances": [], "Parents": []}, {"Name": "Wheel", "Confidence": 99.02688598632812, "Instances": [{"BoundingBox": {"Width": 0.15294162929058075, "Height": 0.11827433854341507, "Left": 0.5159204602241516, "Top": 0.8798494935035706}, "Confidence": 99.02688598632812}, {"BoundingBox": {"Width": 0.15899237990379333, "Height": 0.138827845454216, "Left": 0.8397576212882996, "Top": 0.8592959642410278}, "Confidence": 64.53467559814453}], "Parents": [{"Name": "Machine"}]}, {"Name": "Machine", "Confidence": 99.02688598632812, "Instances": [], "Parents": []}, {"Name": "Shipping Container", "Confidence": 88.18869018554688, "Instances": [], "Parents": []}, {"Name": "Train", "Confidence": 84.63199615478516, "Instances": [{"BoundingBox": {"Width": 0.6736068725585938, "Height": 0.3744034171104431, "Left": 0.31145069003105164, "Top": 0.2034485787153244}, "Confidence": 84.63199615478516}], "Parents": [{"Name": "Vehicle"}, {"Name": "Transportation"}]}]