[{"Name": "Wheel", "Confidence": 99.93461608886719, "Instances": [{"BoundingBox": {"Width": 0.26596885919570923, "Height": 0.37672555446624756, "Left": 0.7332820892333984, "Top": 0.5304859280586243}, "Confidence": 99.93461608886719}, {"BoundingBox": {"Width": 0.37572500109672546, "Height": 0.4014703631401062, "Left": 0.00034812898957170546, "Top": 0.5049035549163818}, "Confidence": 99.42378997802734}], "Parents": [{"Name": "Machine"}]}, {"Name": "Machine", "Confidence": 99.93461608886719, "Instances": [], "Parents": []}, {"Name": "Bicycle", "Confidence": 99.72481536865234, "Instances": [{"BoundingBox": {"Width": 0.9092516303062439, "Height": 0.63271564245224, "Left": 0.04634612053632736, "Top": 0.2686736285686493}, "Confidence": 99.72481536865234}], "Parents": [{"Name": "Vehicle"}, {"Name": "Transportation"}]}, {"Name": "Bike", "Confidence": 99.72481536865234, "Instances": [], "Parents": [{"Name": "Vehicle"}, {"Name": "Transportation"}]}, {"Name": "Vehicle", "Confidence": 99.72481536865234, "Instances": [], "Parents": [{"Name": "Transportation"}]}, {"Name": "Transportation", "Confidence": 99.72481536865234, "Instances": [], "Parents": []}, {"Name": "Person", "Confidence": 99.71905517578125, "Instances": [{"BoundingBox": {"Width": 0.5756276249885559, "Height": 0.6572703123092651, "Left": 0.306968629360199, "Top": 0.0669531300663948}, "Confidence": 99.71905517578125}, {"BoundingBox": {"Width": 0.3783774673938751, "Height": 0.6774963736534119, "Left": 0.026696080341935158, "Top": 0.10901197046041489}, "Confidence": 99.43991088867188}], "Parents": []}, {"Name": "Human", "Confidence": 99.71905517578125, "Instances": [], "Parents": []}, {"Name": "Mountain Bike", "Confidence": 99.51959991455078, "Instances": [], "Parents": [{"Name": "Bicycle"}, {"Name": "Vehicle"}, {"Name": "Transportation"}]}]