[{"Name": "Bicycle", "Confidence": 99.79107666015625, "Instances": [{"BoundingBox": {"Width": 0.28029143810272217, "Height": 0.5625044703483582, "Left": 0.1984098255634308, "Top": 0.2878815233707428}, "Confidence": 99.79107666015625}], "Parents": [{"Name": "Vehicle"}, {"Name": "Transportation"}]}, {"Name": "Vehicle", "Confidence": 99.79107666015625, "Instances": [], "Parents": [{"Name": "Transportation"}]}, {"Name": "Transportation", "Confidence": 99.79107666015625, "Instances": [], "Parents": []}, {"Name": "Helmet", "Confidence": 99.6610336303711, "Instances": [{"BoundingBox": {"Width": 0.07156813144683838, "Height": 0.14724645018577576, "Left": 0.2494727224111557, "Top": 0.07476997375488281}, "Confidence": 99.6610336303711}], "Parents": [{"Name": "Clothing"}]}, {"Name": "Clothing", "Confidence": 99.6610336303711, "Instances": [], "Parents": []}, {"Name": "Person", "Confidence": 99.54927062988281, "Instances": [{"BoundingBox": {"Width": 0.2604388892650604, "Height": 0.6109920740127563, "Left": 0.2022651731967926, "Top": 0.07751194387674332}, "Confidence": 99.54927062988281}], "Parents": []}, {"Name": "Mountain Bike", "Confidence": 98.00538635253906, "Instances": [], "Parents": [{"Name": "Bicycle"}, {"Name": "Vehicle"}, {"Name": "Transportation"}]}, {"Name": "Wheel", "Confidence": 97.47930145263672, "Instances": [{"BoundingBox": {"Width": 0.10846812278032303, "Height": 0.3377061188220978, "Left": 0.35611140727996826, "Top": 0.49390798807144165}, "Confidence": 97.47930145263672}], "Parents": [{"Name": "Machine"}]}, {"Name": "Machine", "Confidence": 97.47930145263672, "Instances": [], "Parents": []}, {"Name": "Slope", "Confidence": 94.41231536865234, "Instances": [], "Parents": []}]