[{"Name": "Person", "Confidence": 99.13681030273438, "Instances": [{"BoundingBox": {"Width": 0.8078709244728088, "Height": 0.9687846899032593, "Left": 0.0, "Top": 0.009459209628403187}, "Confidence": 99.13681030273438}], "Parents": []}, {"Name": "Human", "Confidence": 99.13681030273438, "Instances": [], "Parents": []}, {"Name": "Face", "Confidence": 97.36664581298828, "Instances": [], "Parents": [{"Name": "Person"}]}, {"Name": "Female", "Confidence": 86.57463073730469, "Instances": [], "Parents": [{"Name": "Person"}]}]