[{"Name": "Wheel", "Confidence": 99.91845703125, "Instances": [{"BoundingBox": {"Width": 0.20291273295879364, "Height": 0.37881001830101013, "Left": 0.47161003947257996, "Top": 0.5045163035392761}, "Confidence": 99.91845703125}, {"BoundingBox": {"Width": 0.16704440116882324, "Height": 0.3273303210735321, "Left": 0.26806145906448364, "Top": 0.36056873202323914}, "Confidence": 99.87555694580078}], "Parents": [{"Name": "Machine"}]}, {"Name": "Machine", "Confidence": 99.91845703125, "Instances": [], "Parents": []}, {"Name": "Bicycle", "Confidence": 99.9133529663086, "Instances": [{"BoundingBox": {"Width": 0.43124788999557495, "Height": 0.5725133419036865, "Left": 0.26347148418426514, "Top": 0.2962746322154999}, "Confidence": 99.9133529663086}], "Parents": [{"Name": "Vehicle"}, {"Name": "Transportation"}]}, {"Name": "Vehicle", "Confidence": 99.9133529663086, "Instances": [], "Parents": [{"Name": "Transportation"}]}, {"Name": "Transportation", "Confidence": 99.9133529663086, "Instances": [], "Parents": []}, {"Name": "Person", "Confidence": 99.63130950927734, "Instances": [{"BoundingBox": {"Width": 0.3026977479457855, "Height": 0.5928219556808472, "Left": 0.3834485411643982, "Top": 0.09012413769960403}, "Confidence": 99.63130950927734}], "Parents": []}, {"Name": "Mountain Bike", "Confidence": 97.89781188964844, "Instances": [], "Parents": [{"Name": "Bicycle"}, {"Name": "Vehicle"}, {"Name": "Transportation"}]}, {"Name": "Slope", "Confidence": 85.08998107910156, "Instances": [], "Parents": []}, {"Name": "Helmet", "Confidence": 83.71495819091797, "Instances": [{"BoundingBox": {"Width": 0.08184026181697845, "Height": 0.14064787328243256, "Left": 0.5979012250900269, "Top": 0.08291429281234741}, "Confidence": 83.71495819091797}], "Parents": [{"Name": "Clothing"}]}, {"Name": "Clothing", "Confidence": 83.71495819091797, "Instances": [], "Parents": []}]