[{"Name": "Bicycle", "Confidence": 99.9516372680664, "Instances": [{"BoundingBox": {"Width": 0.197193905711174, "Height": 0.3921894133090973, "Left": 0.2522086203098297, "Top": 0.5422610640525818}, "Confidence": 99.9516372680664}], "Parents": [{"Name": "Vehicle"}, {"Name": "Transportation"}]}, {"Name": "Bike", "Confidence": 99.9516372680664, "Instances": [], "Parents": [{"Name": "Vehicle"}, {"Name": "Transportation"}]}, {"Name": "Vehicle", "Confidence": 99.9516372680664, "Instances": [], "Parents": [{"Name": "Transportation"}]}, {"Name": "Transportation", "Confidence": 99.9516372680664, "Instances": [], "Parents": []}, {"Name": "Person", "Confidence": 99.84464263916016, "Instances": [{"BoundingBox": {"Width": 0.18009041249752045, "Height": 0.4767795503139496, "Left": 0.24820047616958618, "Top": 0.35144728422164917}, "Confidence": 99.84464263916016}], "Parents": []}, {"Name": "Human", "Confidence": 99.84464263916016, "Instances": [], "Parents": []}, {"Name": "Wheel", "Confidence": 98.48439025878906, "Instances": [{"BoundingBox": {"Width": 0.08428791910409927, "Height": 0.27239328622817993, "Left": 0.27790796756744385, "Top": 0.6561481952667236}, "Confidence": 98.48439025878906}, {"BoundingBox": {"Width": 0.06486112624406815, "Height": 0.18122126162052155, "Left": 0.37758105993270874, "Top": 0.6408084034919739}, "Confidence": 96.62757110595703}], "Parents": [{"Name": "Machine"}]}, {"Name": "Machine", "Confidence": 98.48439025878906, "Instances": [], "Parents": []}, {"Name": "Mountain Bike", "Confidence": 98.27413940429688, "Instances": [], "Parents": [{"Name": "Bicycle"}, {"Name": "Vehicle"}, {"Name": "Transportation"}]}]