[{"Name": "Person", "Confidence": 99.75804138183594, "Instances": [{"BoundingBox": {"Width": 0.08929070085287094, "Height": 0.23327459394931793, "Left": 0.36818939447402954, "Top": 0.3621969223022461}, "Confidence": 99.75804138183594}], "Parents": []}, {"Name": "Human", "Confidence": 99.75804138183594, "Instances": [], "Parents": []}, {"Name": "Bicycle", "Confidence": 99.53095245361328, "Instances": [{"BoundingBox": {"Width": 0.20318959653377533, "Height": 0.20778557658195496, "Left": 0.2994399666786194, "Top": 0.44319018721580505}, "Confidence": 99.53095245361328}], "Parents": [{"Name": "Vehicle"}, {"Name": "Transportation"}]}, {"Name": "Bike", "Confidence": 99.53095245361328, "Instances": [], "Parents": [{"Name": "Vehicle"}, {"Name": "Transportation"}]}, {"Name": "Transportation", "Confidence": 99.53095245361328, "Instances": [], "Parents": []}, {"Name": "Vehicle", "Confidence": 99.53095245361328, "Instances": [], "Parents": [{"Name": "Transportation"}]}, {"Name": "Wheel", "Confidence": 98.76823425292969, "Instances": [{"BoundingBox": {"Width": 0.08372073620557785, "Height": 0.1305345743894577, "Left": 0.4189435839653015, "Top": 0.5224611759185791}, "Confidence": 98.76823425292969}, {"BoundingBox": {"Width": 0.08072607219219208, "Height": 0.11775843799114227, "Left": 0.2994866967201233, "Top": 0.4954099953174591}, "Confidence": 92.17189025878906}], "Parents": [{"Name": "Machine"}]}, {"Name": "Machine", "Confidence": 98.76823425292969, "Instances": [], "Parents": []}, {"Name": "Mountain Bike", "Confidence": 90.5235595703125, "Instances": [], "Parents": [{"Name": "Bicycle"}, {"Name": "Vehicle"}, {"Name": "Transportation"}]}]