[{"Name": "Bicycle", "Confidence": 95.1636962890625, "Instances": [{"BoundingBox": {"Width": 0.7769596576690674, "Height": 0.9573085308074951, "Left": 0.12028452754020691, "Top": 0.03263828903436661}, "Confidence": 95.1636962890625}], "Parents": [{"Name": "Vehicle"}, {"Name": "Transportation"}]}, {"Name": "Transportation", "Confidence": 95.1636962890625, "Instances": [], "Parents": []}, {"Name": "Vehicle", "Confidence": 95.1636962890625, "Instances": [], "Parents": [{"Name": "Transportation"}]}, {"Name": "Bike", "Confidence": 95.1636962890625, "Instances": [], "Parents": [{"Name": "Vehicle"}, {"Name": "Transportation"}]}]