[{"Name": "Bicycle", "Confidence": 98.02831268310547, "Instances": [{"BoundingBox": {"Width": 0.9515870809555054, "Height": 0.9297031760215759, "Left": 0.025279616937041283, "Top": 0.05282999575138092}, "Confidence": 98.02831268310547}], "Parents": [{"Name": "Vehicle"}, {"Name": "Transportation"}]}, {"Name": "Transportation", "Confidence": 98.02831268310547, "Instances": [], "Parents": []}, {"Name": "Vehicle", "Confidence": 98.02831268310547, "Instances": [], "Parents": [{"Name": "Transportation"}]}, {"Name": "Bike", "Confidence": 98.02831268310547, "Instances": [], "Parents": [{"Name": "Vehicle"}, {"Name": "Transportation"}]}, {"Name": "Machine", "Confidence": 92.793212890625, "Instances": [], "Parents": []}, {"Name": "Spoke", "Confidence": 82.95637512207031, "Instances": [], "Parents": [{"Name": "Machine"}]}]