[{"Name": "Wheel", "Confidence": 99.99752807617188, "Instances": [{"BoundingBox": {"Width": 0.5513089299201965, "Height": 0.43438956141471863, "Left": 0.19964540004730225, "Top": 0.4911327660083771}, "Confidence": 99.99752807617188}], "Parents": [{"Name": "Machine"}]}, {"Name": "Machine", "Confidence": 99.99752807617188, "Instances": [], "Parents": []}, {"Name": "Bicycle", "Confidence": 99.9062271118164, "Instances": [{"BoundingBox": {"Width": 0.7874065637588501, "Height": 0.6803181767463684, "Left": 0.2023507058620453, "Top": 0.25806382298469543}, "Confidence": 99.9062271118164}], "Parents": [{"Name": "Vehicle"}, {"Name": "Transportation"}]}, {"Name": "Bike", "Confidence": 99.9062271118164, "Instances": [], "Parents": [{"Name": "Vehicle"}, {"Name": "Transportation"}]}, {"Name": "Vehicle", "Confidence": 99.9062271118164, "Instances": [], "Parents": [{"Name": "Transportation"}]}, {"Name": "Transportation", "Confidence": 99.9062271118164, "Instances": [], "Parents": []}, {"Name": "Mountain Bike", "Confidence": 92.0974349975586, "Instances": [], "Parents": [{"Name": "Bicycle"}, {"Name": "Vehicle"}, {"Name": "Transportation"}]}, {"Name": "Car", "Confidence": 86.07369232177734, "Instances": [{"BoundingBox": {"Width": 0.10869479924440384, "Height": 0.0913124606013298, "Left": 0.8895247578620911, "Top": 0.32596686482429504}, "Confidence": 86.07369232177734}], "Parents": [{"Name": "Vehicle"}, {"Name": "Transportation"}]}, {"Name": "Automobile", "Confidence": 86.07369232177734, "Instances": [], "Parents": [{"Name": "Vehicle"}, {"Name": "Transportation"}]}]